LiDAR_Lite.py
LiDAR_Lite-0.1.0.dist-info/DESCRIPTION.rst
LiDAR_Lite-0.1.0.dist-info/METADATA
LiDAR_Lite-0.1.0.dist-info/RECORD
LiDAR_Lite-0.1.0.dist-info/WHEEL
LiDAR_Lite-0.1.0.dist-info/metadata.json
LiDAR_Lite-0.1.0.dist-info/top_level.txt
