Metadata-Version: 2.0
Name: LiDAR-Lite
Version: 0.1.0
Summary: LiDAR-Lite v3 Python Interface
Home-page: https://github.gatech.edu/VIP-Automotive-LiDAR-OE-Subgroup/LiDAR-Lite
Author: Kevin Abraham
Author-email: kev@gatech.edu
License: Apache-2.0
Keywords: LiDAR Lite LiDAR-Lite Garmin
Platform: UNKNOWN
Classifier: Development Status :: 3 - Alpha
Classifier: Intended Audience :: Developers
Classifier: Topic :: Other/Nonlisted Topic
Classifier: License :: OSI Approved :: Apache Software License
Classifier: Programming Language :: Python :: 3 :: Only
Requires-Python: >=3, <4
Requires-Dist: smbus2
